{
  "total": 6,
  "live_1": {
    "file": "images/l_1.jpg",
    "url": "a.html",
    "status": "방송예정",
    "company": "소담상회 x 에이브랩",
    "date": "10월31일 (화)",
    "time": "16:00"
  },
  "live_2": {
    "file": "images/v2.jpg",
    "url": "b.html"
  },
  "live_3": {
    "file": "images/v3.jpg",
    "url": "c.html"
  },
  "live_4": {
    "file": "images/v4.jpg",
    "url": "d.html"
  },
  "live_5": {
    "file": "images/v5.jpg",
    "url": "e.html"
  },
  "live_6": {
    "file": "images/v6.png",
    "url": "f.html"
  }
}
